AUTHORS
ChangeLog
LICENSE
MANIFEST.in
README.md
README.rst
requirements.txt
setup.cfg
setup.py
test-requirements.txt
galley/__init__.py
galley/builder.py
galley/shell.py
galley/test.py
galley.egg-info/PKG-INFO
galley.egg-info/SOURCES.txt
galley.egg-info/dependency_links.txt
galley.egg-info/entry_points.txt
galley.egg-info/not-zip-safe
galley.egg-info/requires.txt
galley.egg-info/top_level.txt