Metadata-Version: 1.0
Name: galley
Version: 0.2.1
Summary: End-to-end test orchestration with Docker
Home-page: http://github.com/rackerlabs/galley
Author: Ryan Walker
Author-email: ryan@wlkr.io
License: UNKNOWN
Platform: UNKNOWN
